easy_framework/__init__.py
easy_framework/_context.py
easy_framework/_meta.py
easy_framework/auth/__init__.py
easy_framework/auth/_authManager.py
easy_framework/auth/_authModel.py
easy_framework/auth/_authModelMongo.py
easy_framework/auth/_authSerializer.py
easy_framework/auth/_authView.py
easy_framework/auth/_baseAuthMethod.py
easy_framework/auth/_databaseMethodMongo.py
easy_framework/auth/_databaseMethodSql.py
easy_framework/auth/_password.py
easy_framework/config.py
easy_framework/database/__init__.py
easy_framework/database/mongo/__init__.py
easy_framework/database/mongo/_mongodb.py
easy_framework/database/sql/__init__.py
easy_framework/database/sql/_base.py
easy_framework/database/sql/_dbConfig.py
easy_framework/database/sql/_sqldb.py
easy_framework/decorators.py
easy_framework/easy_framework.py
easy_framework/exception/__init__.py
easy_framework/exception/apiExceptions.py
easy_framework/exception/baseException.py
easy_framework/model/__init__.py
easy_framework/model/_baseModelMongo.py
easy_framework/model/_baseModelSql.py
easy_framework/model/_utils.py
easy_framework/serializer/__init__.py
easy_framework/serializer/_baseSerializerMongo.py
easy_framework/serializer/_baseSerializerSql.py
easy_framework/user/__init__.py
easy_framework/user/userManager.py
easy_framework/user/userMixin.py
easy_framework/user/userModel.py
easy_framework/user/userModelMongo.py
easy_framework/user/utils.py
easy_framework/validator/__init__.py
easy_framework/validator/_baseValidator.py
easy_framework/validator/_login_required.py
easy_framework/validator/_self_required.py
easy_framework/view/__init__.py
easy_framework/view/_genericApiView.py
easy_framework/view/_utils.py
easy_framework/view/_viewHandler.py
easy_framework-0.0.3.dist-info/LICENSE
easy_framework-0.0.3.dist-info/METADATA
easy_framework-0.0.3.dist-info/WHEEL
easy_framework-0.0.3.dist-info/RECORD
